[
  {
    "id":1,
    "no_tickets":57,
    "price":"$54.38",
    "x_coord":4,
    "y_coord":0
  },
  {
    "id":2,
    "no_tickets":49,
    "price":"$73.43",
    "x_coord":-7,
    "y_coord":-3
  },
  {
    "id":3,
    "no_tickets":6,
    "price":"$73.87",
    "x_coord":3,
    "y_coord":0
  },
  {
    "id":4,
    "no_tickets":27,
    "price":"$34.37",
    "x_coord":9,
    "y_coord":-3
  },
  {
    "id":5,
    "no_tickets":66,
    "price":"$20.41",
    "x_coord":-8,
    "y_coord":-4
  },
  {
    "id":6,
    "no_tickets":94,
    "price":"$31.74",
    "x_coord":10,
    "y_coord":9
  },
  {
    "id":7,
    "no_tickets":42,
    "price":"$0.79",
    "x_coord":1,
    "y_coord":9
  },
  {
    "id":8,
    "no_tickets":44,
    "price":"$42.73",
    "x_coord":1,
    "y_coord":-7
  },
  {
    "id":9,
    "no_tickets":87,
    "price":"$90.14",
    "x_coord":0,
    "y_coord":1
  },
  {
    "id":10,
    "no_tickets":57,
    "price":"$71.48",
    "x_coord":9,
    "y_coord":6
  },
  {
    "id":11,
    "no_tickets":99,
    "price":"$44.30",
    "x_coord":3,
    "y_coord":5
  },
  {
    "id":12,
    "no_tickets":14,
    "price":"$59.36",
    "x_coord":5,
    "y_coord":-7
  },
  {
    "id":13,
    "no_tickets":30,
    "price":"$27.43",
    "x_coord":3,
    "y_coord":-10
  },
  {
    "id":14,
    "no_tickets":41,
    "price":"$20.50",
    "x_coord":-3,
    "y_coord":-4
  },
  {
    "id":15,
    "no_tickets":13,
    "price":"$70.16",
    "x_coord":-8,
    "y_coord":2
  },
  {
    "id":16,
    "no_tickets":41,
    "price":"$24.54",
    "x_coord":8,
    "y_coord":8
  },
  {
    "id":17,
    "no_tickets":33,
    "price":"$33.80",
    "x_coord":-3,
    "y_coord":10
  },
  {
    "id":18,
    "no_tickets":1,
    "price":"$33.62",
    "x_coord":5,
    "y_coord":-6
  },
  {
    "id":19,
    "no_tickets":56,
    "price":"$12.36",
    "x_coord":-8,
    "y_coord":9
  },
  {
    "id":20,
    "no_tickets":63,
    "price":"$93.85",
    "x_coord":-2,
    "y_coord":1
  },
  {
    "id":21,
    "no_tickets":65,
    "price":"$52.29",
    "x_coord":0,
    "y_coord":-9
  },
  {
    "id":22,
    "no_tickets":63,
    "price":"$29.71",
    "x_coord":6,
    "y_coord":0
  },
  {
    "id":23,
    "no_tickets":98,
    "price":"$72.52",
    "x_coord":3,
    "y_coord":0
  },
  {
    "id":24,
    "no_tickets":98,
    "price":"$49.03",
    "x_coord":8,
    "y_coord":6
  },
  {
    "id":25,
    "no_tickets":9,
    "price":"$93.76",
    "x_coord":-6,
    "y_coord":-8
  },
  {
    "id":26,
    "no_tickets":87,
    "price":"$87.50",
    "x_coord":0,
    "y_coord":1
  },
  {
    "id":27,
    "no_tickets":19,
    "price":"$42.41",
    "x_coord":-2,
    "y_coord":-2
  },
  {
    "id":28,
    "no_tickets":71,
    "price":"$72.65",
    "x_coord":0,
    "y_coord":5
  },
  {
    "id":29,
    "no_tickets":11,
    "price":"$40.87",
    "x_coord":-3,
    "y_coord":7
  },
  {
    "id":30,
    "no_tickets":77,
    "price":"$7.33",
    "x_coord":8,
    "y_coord":-1
  },
  {
    "id":31,
    "no_tickets":43,
    "price":"$54.82",
    "x_coord":-8,
    "y_coord":3
  },
  {
    "id":32,
    "no_tickets":91,
    "price":"$63.85",
    "x_coord":-7,
    "y_coord":1
  },
  {
    "id":33,
    "no_tickets":2,
    "price":"$72.88",
    "x_coord":-2,
    "y_coord":-10
  },
  {
    "id":34,
    "no_tickets":11,
    "price":"$9.14",
    "x_coord":-5,
    "y_coord":-4
  },
  {
    "id":35,
    "no_tickets":64,
    "price":"$14.47",
    "x_coord":-4,
    "y_coord":8
  },
  {
    "id":36,
    "no_tickets":26,
    "price":"$26.61",
    "x_coord":-2,
    "y_coord":-8
  },
  {
    "id":37,
    "no_tickets":57,
    "price":"$36.53",
    "x_coord":0,
    "y_coord":2
  },
  {
    "id":38,
    "no_tickets":73,
    "price":"$99.65",
    "x_coord":1,
    "y_coord":10
  },
  {
    "id":39,
    "no_tickets":96,
    "price":"$87.74",
    "x_coord":6,
    "y_coord":-5
  },
  {
    "id":40,
    "no_tickets":9,
    "price":"$71.57",
    "x_coord":1,
    "y_coord":-8
  },
  {
    "id":41,
    "no_tickets":78,
    "price":"$35.37",
    "x_coord":9,
    "y_coord":3
  },
  {
    "id":42,
    "no_tickets":81,
    "price":"$2.28",
    "x_coord":-10,
    "y_coord":6
  },
  {
    "id":43,
    "no_tickets":94,
    "price":"$63.88",
    "x_coord":-1,
    "y_coord":-1
  },
  {
    "id":44,
    "no_tickets":16,
    "price":"$66.26",
    "x_coord":-6,
    "y_coord":-9
  },
  {
    "id":45,
    "no_tickets":36,
    "price":"$7.47",
    "x_coord":2,
    "y_coord":-5
  },
  {
    "id":46,
    "no_tickets":72,
    "price":"$31.65",
    "x_coord":3,
    "y_coord":2
  },
  {
    "id":47,
    "no_tickets":71,
    "price":"$73.66",
    "x_coord":-1,
    "y_coord":3
  },
  {
    "id":48,
    "no_tickets":55,
    "price":"$56.93",
    "x_coord":-5,
    "y_coord":8
  },
  {
    "id":49,
    "no_tickets":61,
    "price":"$75.96",
    "x_coord":-2,
    "y_coord":3
  },
  {
    "id":50,
    "no_tickets":72,
    "price":"$24.21",
    "x_coord":-6,
    "y_coord":-5
  },
  {
    "id":51,
    "no_tickets":9,
    "price":"$55.38",
    "x_coord":4,
    "y_coord":-8
  },
  {
    "id":52,
    "no_tickets":90,
    "price":"$1.47",
    "x_coord":-9,
    "y_coord":-9
  },
  {
    "id":53,
    "no_tickets":18,
    "price":"$35.70",
    "x_coord":-8,
    "y_coord":-6
  },
  {
    "id":54,
    "no_tickets":72,
    "price":"$31.43",
    "x_coord":-5,
    "y_coord":-10
  },
  {
    "id":55,
    "no_tickets":57,
    "price":"$2.52",
    "x_coord":2,
    "y_coord":6
  },
  {
    "id":56,
    "no_tickets":71,
    "price":"$98.59",
    "x_coord":-6,
    "y_coord":-3
  },
  {
    "id":57,
    "no_tickets":41,
    "price":"$32.11",
    "x_coord":-5,
    "y_coord":-4
  },
  {
    "id":58,
    "no_tickets":14,
    "price":"$45.13",
    "x_coord":3,
    "y_coord":-6
  },
  {
    "id":59,
    "no_tickets":60,
    "price":"$33.44",
    "x_coord":10,
    "y_coord":4
  },
  {
    "id":60,
    "no_tickets":29,
    "price":"$39.72",
    "x_coord":-9,
    "y_coord":2
  },
  {
    "id":61,
    "no_tickets":67,
    "price":"$84.66",
    "x_coord":5,
    "y_coord":7
  },
  {
    "id":62,
    "no_tickets":41,
    "price":"$61.98",
    "x_coord":9,
    "y_coord":-4
  },
  {
    "id":63,
    "no_tickets":70,
    "price":"$42.84",
    "x_coord":-10,
    "y_coord":-3
  },
  {
    "id":64,
    "no_tickets":95,
    "price":"$70.17",
    "x_coord":10,
    "y_coord":-6
  },
  {
    "id":65,
    "no_tickets":3,
    "price":"$57.63",
    "x_coord":7,
    "y_coord":10
  },
  {
    "id":66,
    "no_tickets":54,
    "price":"$32.97",
    "x_coord":7,
    "y_coord":-4
  },
  {
    "id":67,
    "no_tickets":8,
    "price":"$21.02",
    "x_coord":9,
    "y_coord":8
  },
  {
    "id":68,
    "no_tickets":2,
    "price":"$8.51",
    "x_coord":-6,
    "y_coord":0
  },
  {
    "id":69,
    "no_tickets":69,
    "price":"$39.41",
    "x_coord":-5,
    "y_coord":9
  },
  {
    "id":70,
    "no_tickets":27,
    "price":"$93.14",
    "x_coord":-9,
    "y_coord":-5
  },
  {
    "id":71,
    "no_tickets":43,
    "price":"$49.20",
    "x_coord":10,
    "y_coord":-10
  },
  {
    "id":72,
    "no_tickets":15,
    "price":"$59.63",
    "x_coord":-5,
    "y_coord":-10
  },
  {
    "id":73,
    "no_tickets":68,
    "price":"$35.30",
    "x_coord":6,
    "y_coord":4
  },
  {
    "id":74,
    "no_tickets":64,
    "price":"$33.21",
    "x_coord":5,
    "y_coord":-1
  },
  {
    "id":75,
    "no_tickets":63,
    "price":"$6.09",
    "x_coord":8,
    "y_coord":-8
  },
  {
    "id":76,
    "no_tickets":66,
    "price":"$91.13",
    "x_coord":9,
    "y_coord":3
  },
  {
    "id":77,
    "no_tickets":76,
    "price":"$15.86",
    "x_coord":-7,
    "y_coord":-9
  },
  {
    "id":78,
    "no_tickets":97,
    "price":"$92.57",
    "x_coord":-10,
    "y_coord":-3
  },
  {
    "id":79,
    "no_tickets":27,
    "price":"$53.11",
    "x_coord":8,
    "y_coord":-4
  },
  {
    "id":80,
    "no_tickets":54,
    "price":"$52.26",
    "x_coord":-8,
    "y_coord":9
  },
  {
    "id":81,
    "no_tickets":64,
    "price":"$11.39",
    "x_coord":-7,
    "y_coord":-5
  },
  {
    "id":82,
    "no_tickets":78,
    "price":"$21.48",
    "x_coord":10,
    "y_coord":3
  },
  {
    "id":83,
    "no_tickets":38,
    "price":"$35.85",
    "x_coord":-4,
    "y_coord":1
  },
  {
    "id":84,
    "no_tickets":35,
    "price":"$0.79",
    "x_coord":6,
    "y_coord":-9
  },
  {
    "id":85,
    "no_tickets":29,
    "price":"$15.50",
    "x_coord":-1,
    "y_coord":-1
  },
  {
    "id":86,
    "no_tickets":53,
    "price":"$52.40",
    "x_coord":2,
    "y_coord":-6
  },
  {
    "id":87,
    "no_tickets":86,
    "price":"$6.82",
    "x_coord":7,
    "y_coord":-7
  },
  {
    "id":88,
    "no_tickets":82,
    "price":"$18.22",
    "x_coord":-2,
    "y_coord":-10
  },
  {
    "id":89,
    "no_tickets":68,
    "price":"$73.22",
    "x_coord":-7,
    "y_coord":-1
  },
  {
    "id":90,
    "no_tickets":92,
    "price":"$31.26",
    "x_coord":-5,
    "y_coord":-6
  },
  {
    "id":91,
    "no_tickets":99,
    "price":"$11.28",
    "x_coord":-5,
    "y_coord":-2
  },
  {
    "id":92,
    "no_tickets":12,
    "price":"$50.27",
    "x_coord":5,
    "y_coord":3
  },
  {
    "id":93,
    "no_tickets":75,
    "price":"$74.41",
    "x_coord":-8,
    "y_coord":-6
  },
  {
    "id":94,
    "no_tickets":65,
    "price":"$89.28",
    "x_coord":-9,
    "y_coord":-2
  },
  {
    "id":95,
    "no_tickets":76,
    "price":"$13.15",
    "x_coord":0,
    "y_coord":8
  },
  {
    "id":96,
    "no_tickets":78,
    "price":"$4.23",
    "x_coord":-3,
    "y_coord":10
  },
  {
    "id":97,
    "no_tickets":71,
    "price":"$25.17",
    "x_coord":-9,
    "y_coord":0
  },
  {
    "id":98,
    "no_tickets":5,
    "price":"$57.74",
    "x_coord":10,
    "y_coord":-1
  },
  {
    "id":99,
    "no_tickets":88,
    "price":"$4.37",
    "x_coord":5,
    "y_coord":9
  },
  {
    "id":100,
    "no_tickets":44,
    "price":"$20.13",
    "x_coord":8,
    "y_coord":-10
  }
]
